odoo/addons/l10n_nl_tax_statement_date_range/README.rst
odoo/addons/l10n_nl_tax_statement_date_range/__init__.py
odoo/addons/l10n_nl_tax_statement_date_range/__manifest__.py
odoo/addons/l10n_nl_tax_statement_date_range/i18n/l10n_nl_tax_statement_date_range.pot
odoo/addons/l10n_nl_tax_statement_date_range/models/__init__.py
odoo/addons/l10n_nl_tax_statement_date_range/models/l10n_nl_vat_statement.py
odoo/addons/l10n_nl_tax_statement_date_range/readme/CONTRIBUTORS.md
odoo/addons/l10n_nl_tax_statement_date_range/readme/DESCRIPTION.md
odoo/addons/l10n_nl_tax_statement_date_range/readme/INSTALL.md
odoo/addons/l10n_nl_tax_statement_date_range/readme/USAGE.md
odoo/addons/l10n_nl_tax_statement_date_range/static/description/icon.png
odoo/addons/l10n_nl_tax_statement_date_range/static/description/index.html
odoo/addons/l10n_nl_tax_statement_date_range/tests/__init__.py
odoo/addons/l10n_nl_tax_statement_date_range/tests/test_l10n_nl_vat_statement.py
odoo/addons/l10n_nl_tax_statement_date_range/views/l10n_nl_vat_statement_view.xml
odoo_addon_l10n_nl_tax_statement_date_range-18.0.1.0.0.2.dist-info/METADATA
odoo_addon_l10n_nl_tax_statement_date_range-18.0.1.0.0.2.dist-info/WHEEL
odoo_addon_l10n_nl_tax_statement_date_range-18.0.1.0.0.2.dist-info/top_level.txt
odoo_addon_l10n_nl_tax_statement_date_range-18.0.1.0.0.2.dist-info/RECORD
